dynattr/__init__.py
dynattr/_modidx.py
dynattr/core.py
dynattr-0.0.5.dist-info/LICENSE
dynattr-0.0.5.dist-info/METADATA
dynattr-0.0.5.dist-info/WHEEL
dynattr-0.0.5.dist-info/entry_points.txt
dynattr-0.0.5.dist-info/top_level.txt
dynattr-0.0.5.dist-info/RECORD
