Metadata-Version: 2.1
Name: dynattr
Version: 0.0.5
Summary: Dynamic Attributes Mixin
Home-page: https://github.com/dsm-72/dynattr
Author: dsm-72
Author-email: sumner.magruder@yale.edu
License: Apache Software License 2.0
Keywords: nbdev jupyter notebook python attr dyn dynattr
Classifier: Development Status :: 4 - Beta
Classifier: Intended Audience :: Developers
Classifier: Natural Language :: English
Classifier: Programming Language :: Python :: 3.11
Classifier: License :: OSI Approved :: Apache Software License
Requires-Python: >=3.11
License-File: LICENSE
Requires-Dist: atyp
Requires-Dist: ispec
Provides-Extra: dev
